automl/__init__.py
automl/models/__init__.py
automl/models/getclassification.py
automl/models/getregression.py
automl/models/utils.py
automl/models/basemodels/__init__.py
automl/models/basemodels/classifiers.py
automl/models/basemodels/ensemblers.py
automl/models/basemodels/regressors.py
automl/models/mlalgos/__init__.py
automl/models/mlalgos/classification.py
automl/models/mlalgos/ensemble.py
automl/models/mlalgos/regression.py
automl/preprocessing/__init__.py
automl/preprocessing/preprocessor.py
automl/preprocessing/utils.py
light_automl-1.0.1.dist-info/LICENSE
light_automl-1.0.1.dist-info/METADATA
light_automl-1.0.1.dist-info/WHEEL
light_automl-1.0.1.dist-info/top_level.txt
light_automl-1.0.1.dist-info/RECORD
