Metadata-Version: 2.1
Name: light-automl
Version: 1.0.1
Summary: UNKNOWN
Home-page: https://github.com/AtufaShireen/lightautoml
Author: Atufa Shireen
License: UNKNOWN
Platform: UNKNOWN
Classifier: Development Status :: 3 - Alpha
Classifier: Intended Audience :: Developers
Classifier: Topic :: Software Development :: Build Tools
Classifier: License :: OSI Approved :: MIT License
Classifier: Programming Language :: Python :: 3
Classifier: Programming Language :: Python :: 3.4
Classifier: Programming Language :: Python :: 3.5
Classifier: Programming Language :: Python :: 3.6
License-File: LICENSE
Requires-Dist: joblib (==1.1.0)
Requires-Dist: kneed (==0.7.0)
Requires-Dist: matplotlib (==3.5.0)
Requires-Dist: numpy (==1.21.4)
Requires-Dist: pandas (==1.3.4)
Requires-Dist: scikit-learn (==0.24.2)
Requires-Dist: scikit-optimize (==0.9.0)
Requires-Dist: scikit-plot (==0.3.7)
Requires-Dist: scipy (==1.7.3)
Requires-Dist: xgboost (==1.5.0)
